Metadata-Version: 2.1
Name: Stiletto
Version: 0.0.1
Summary: A computational model of the cerebral perforating arteries
Home-page: https://www.globalexposome.org/projects/stiletto
Author: Luis Falcon
Author-email: stiletto@globalexposome.org
License: GPL v3+
Download-URL: https://www.gnusolidario.org
Keywords: stiletto
Platform: any
Classifier: Development Status :: 2 - Pre-Alpha
Classifier: Environment :: X11 Applications :: Qt
Classifier: Intended Audience :: Developers
Classifier: Intended Audience :: End Users/Desktop
Classifier: Intended Audience :: Healthcare Industry
Classifier: Intended Audience :: Science/Research
Classifier: License :: OSI Approved :: GNU General Public License (GPL)
Classifier: Operating System :: POSIX
Classifier: Programming Language :: Python :: 3
Classifier: Topic :: Scientific/Engineering :: Bio-Informatics
Classifier: Topic :: Scientific/Engineering :: Medical Science Apps.
Classifier: Natural Language :: English
Requires-Python: >=3.10,<4
License-File: LICENSE
